commitizen_oca/cz_commitizen_oca.py
commitizen_oca-0.2.0.dist-info/METADATA
commitizen_oca-0.2.0.dist-info/WHEEL
commitizen_oca-0.2.0.dist-info/top_level.txt
commitizen_oca-0.2.0.dist-info/RECORD
